mousebrains/__init__.py
mousebrains/__version__.py
mousebrains/core.py
mousebrains/download.py
mousebrains/templates.py
mousebrains/data/template_meta.json
mousebrains/data/uct-to-ccf_landmarks.csv
mousebrains/meshes/AllenCCF.ply
mousebrains-0.0.2.dist-info/LICENSE
mousebrains-0.0.2.dist-info/METADATA
mousebrains-0.0.2.dist-info/WHEEL
mousebrains-0.0.2.dist-info/top_level.txt
mousebrains-0.0.2.dist-info/RECORD
