Metadata-Version: 2.1
Name: mousebrains
Version: 0.0.2
Summary: Transforms to map between different mouse (template) brains
Home-page: https://github.com/navis/navis-mousebrains
Author: Philipp Schlegel
Author-email: pms70@cam.ac.uk
License: GNU GPL V3
Keywords: mouse brains template registration brain navis transform
Classifier: Development Status :: 3 - Alpha
Classifier: Intended Audience :: Science/Research
Classifier: Topic :: Scientific/Engineering :: Bio-Informatics
Classifier: License :: OSI Approved :: GNU General Public License v3 or later (GPLv3+)
Classifier: Programming Language :: Python :: 3
Classifier: Programming Language :: Python :: 3.9
Classifier: Programming Language :: Python :: 3.10
Classifier: Programming Language :: Python :: 3.11
Classifier: Programming Language :: Python :: 3.12
Requires-Python: >=3.9
License-File: LICENSE
Requires-Dist: gitpython
Requires-Dist: navis >=0.6.0
Requires-Dist: numpy
Requires-Dist: pandas
Provides-Extra: extras
